setup.cfg
setup.py
romius/__init__.py
romius/romius.py
romius.egg-info/PKG-INFO
romius.egg-info/SOURCES.txt
romius.egg-info/dependency_links.txt
romius.egg-info/not-zip-safe
romius.egg-info/top_level.txt