Metadata-Version: 1.0
Name: romius
Version: 0.1
Summary: Romius library
Home-page: UNKNOWN
Author: UNKNOWN
Author-email: roman.kuksenko1@gmail.com
License: UNKNOWN
Platform: UNKNOWN
